{
  "broadcastProducts": [
    {
      "index": 508,
      "broadcastIndex": 67,
      "liveEndDate": "2019-10-17T15:19:17",
      "originPrice": 3500,
      "salePrice": 3500,
      "discountRate": 0,
      "product": {
        "number": 511731,
        "name": "PLAMAX MS-01 마신영웅전 와타루 - 센진마루",
        "promotion": "[5월입고완료] ",
        "maxQuantity": 3,
        "stokeCount": 970,
        "reviewCount": 1,
        "averageRating": 2,
        "coupons": [],
        "imageUrls": {
          "origin": "https://sauce.kr.object.ncloudstorage.com/mall/dev/product/511731/9224415955d537cba78f338.042267521565752506.jpg",
          "basic": "https://sauce.kr.object.ncloudstorage.com/mall/dev/product/511731/90x90/9224415955d537cba78f338.042267521565752506.jpg",
          "twice": "https://sauce.kr.object.ncloudstorage.com/mall/dev/product/511731/180x180/9224415955d537cba78f338.042267521565752506.jpg",
          "triple": "https://sauce.kr.object.ncloudstorage.com/mall/dev/product/511731/270x270/9224415955d537cba78f338.042267521565752506.jpg"
        },
        "delivery": {
          "type": 1,
          "fee": 5000,
          "freeAmount": 0,
          "package": true
        },
        "soldOut": false,
        "endOfSale": false
      },
      "live": false
    },
    {
      "index": 509,
      "broadcastIndex": 67,
      "liveEndDate": "2019-10-17T15:19:17",
      "originPrice": 5000,
      "salePrice": 4000,
      "discountRate": 20,
      "product": {
        "number": 511735,
        "name": "묶음 - 무료 - 추가배송비 없음 있음 없음 있음 없음",
        "promotion": "묶음배송 - 무료 배송 - 추가배송비 없음",
        "maxQuantity": 5,
        "stokeCount": 114,
        "reviewCount": 0,
        "averageRating": 0,
        "coupons": [],
        "imageUrls": {
          "origin": "https://sauce.kr.object.ncloudstorage.com/mall/dev/product/511735/15373013015d6777541420d9.698004331567061844.jpg",
          "basic": "https://sauce.kr.object.ncloudstorage.com/mall/dev/product/511735/90x90/15373013015d6777541420d9.698004331567061844.jpg",
          "twice": "https://sauce.kr.object.ncloudstorage.com/mall/dev/product/511735/180x180/15373013015d6777541420d9.698004331567061844.jpg",
          "triple": "https://sauce.kr.object.ncloudstorage.com/mall/dev/product/511735/270x270/15373013015d6777541420d9.698004331567061844.jpg"
        },
        "delivery": {
          "type": 0,
          "fee": 0,
          "freeAmount": 0,
          "package": true
        },
        "soldOut": false,
        "endOfSale": false
      },
      "live": false
    },
    {
      "index": 510,
      "broadcastIndex": 67,
      "liveEndDate": "2019-10-17T15:19:17",
      "originPrice": 6000,
      "salePrice": 4000,
      "discountRate": 33,
      "product": {
        "number": 511736,
        "name": "묶음착불음묶음착불음묶음착불음묶음착불음묶음착불음묶음착불음",
        "promotion": "묶음배송 - 착불 - 3000 - 추가배송비 없음",
        "maxQuantity": 2,
        "stokeCount": 113,
        "reviewCount": 0,
        "averageRating": 0,
        "coupons": [],
        "imageUrls": {
          "origin": "https://sauce.kr.object.ncloudstorage.com/mall/dev/product/511736/11593629795d6778155872c9.831672001567062037.jpg",
          "basic": "https://sauce.kr.object.ncloudstorage.com/mall/dev/product/511736/90x90/11593629795d6778155872c9.831672001567062037.jpg",
          "twice": "https://sauce.kr.object.ncloudstorage.com/mall/dev/product/511736/180x180/11593629795d6778155872c9.831672001567062037.jpg",
          "triple": "https://sauce.kr.object.ncloudstorage.com/mall/dev/product/511736/270x270/11593629795d6778155872c9.831672001567062037.jpg"
        },
        "delivery": {
          "type": 1,
          "fee": 3000,
          "freeAmount": 0,
          "package": true
        },
        "soldOut": false,
        "endOfSale": false
      },
      "live": false
    },
    {
      "index": 511,
      "broadcastIndex": 67,
      "liveEndDate": "2019-10-17T15:19:17",
      "originPrice": 7500,
      "salePrice": 5500,
      "discountRate": 27,
      "product": {
        "number": 511737,
        "name": "123456789012345678901234567890",
        "promotion": "묶음배송 - 선불 - 2500 - 추가배송비 없음",
        "maxQuantity": 1,
        "stokeCount": 5,
        "reviewCount": 1,
        "averageRating": 4,
        "coupons": [],
        "imageUrls": {
          "origin": "https://sauce.kr.object.ncloudstorage.com/mall/dev/product/511737/11019559845d677887d195d1.763175881567062151.jpg",
          "basic": "https://sauce.kr.object.ncloudstorage.com/mall/dev/product/511737/90x90/11019559845d677887d195d1.763175881567062151.jpg",
          "twice": "https://sauce.kr.object.ncloudstorage.com/mall/dev/product/511737/180x180/11019559845d677887d195d1.763175881567062151.jpg",
          "triple": "https://sauce.kr.object.ncloudstorage.com/mall/dev/product/511737/270x270/11019559845d677887d195d1.763175881567062151.jpg"
        },
        "delivery": {
          "type": 2,
          "fee": 2500,
          "freeAmount": 0,
          "package": true
        },
        "soldOut": false,
        "endOfSale": false
      },
      "live": false
    },
    {
      "index": 512,
      "broadcastIndex": 67,
      "liveEndDate": "2019-10-17T15:19:17",
      "originPrice": 7500,
      "salePrice": 4000,
      "discountRate": 47,
      "product": {
        "number": 511740,
        "name": "묶음 - 선불 - 3000 - 추가배송비 없음",
        "promotion": "묶음배송 - 선불 - 3000 - 추가배송비 없음",
        "maxQuantity": 3,
        "stokeCount": 160,
        "reviewCount": 0,
        "averageRating": 0,
        "coupons": [],
        "imageUrls": {
          "origin": "https://sauce.kr.object.ncloudstorage.com/mall/dev/product/511740/112711695d677f0984a652.717137531567063817.jpg",
          "basic": "https://sauce.kr.object.ncloudstorage.com/mall/dev/product/511740/90x90/112711695d677f0984a652.717137531567063817.jpg",
          "twice": "https://sauce.kr.object.ncloudstorage.com/mall/dev/product/511740/180x180/112711695d677f0984a652.717137531567063817.jpg",
          "triple": "https://sauce.kr.object.ncloudstorage.com/mall/dev/product/511740/270x270/112711695d677f0984a652.717137531567063817.jpg"
        },
        "delivery": {
          "type": 2,
          "fee": 3000,
          "freeAmount": 0,
          "package": true
        },
        "soldOut": false,
        "endOfSale": false
      },
      "live": false
    },
    {
      "index": 513,
      "broadcastIndex": 67,
      "liveEndDate": "2019-10-17T15:19:17",
      "originPrice": 1500,
      "salePrice": 1400,
      "discountRate": 7,
      "product": {
        "number": 511741,
        "name": "묶음 - 조건부 - 2500(40000)- 추가배송비 없음",
        "promotion": "묶음배송 - 조건부 무료 - 2500(40000)- 추가배송비 없음",
        "maxQuantity": 50,
        "stokeCount": 62,
        "reviewCount": 1,
        "averageRating": 3,
        "coupons": [],
        "imageUrls": {
          "origin": "https://sauce.kr.object.ncloudstorage.com/mall/dev/product/511741/1819100885d677f7f35c4a3.986274821567063935.jpg",
          "basic": "https://sauce.kr.object.ncloudstorage.com/mall/dev/product/511741/90x90/1819100885d677f7f35c4a3.986274821567063935.jpg",
          "twice": "https://sauce.kr.object.ncloudstorage.com/mall/dev/product/511741/180x180/1819100885d677f7f35c4a3.986274821567063935.jpg",
          "triple": "https://sauce.kr.object.ncloudstorage.com/mall/dev/product/511741/270x270/1819100885d677f7f35c4a3.986274821567063935.jpg"
        },
        "delivery": {
          "type": 3,
          "fee": 2500,
          "freeAmount": 40000,
          "package": true
        },
        "soldOut": false,
        "endOfSale": false
      },
      "live": false
    },
    {
      "index": 514,
      "broadcastIndex": 67,
      "liveEndDate": "2019-10-17T15:19:17",
      "originPrice": 2200,
      "salePrice": 1800,
      "discountRate": 18,
      "product": {
        "number": 511742,
        "name": "묶음 - 조건부 - 3000(20000)- 추가배송비 없음",
        "promotion": "묶음배송 - 조건부 무료 - 3000(20000)- 추가배송비 없음",
        "maxQuantity": 50,
        "stokeCount": 40,
        "reviewCount": 0,
        "averageRating": 0,
        "coupons": [],
        "imageUrls": {
          "origin": "",
          "basic": "",
          "twice": "",
          "triple": ""
        },
        "delivery": {
          "type": 3,
          "fee": 3000,
          "freeAmount": 20000,
          "package": true
        },
        "soldOut": false,
        "endOfSale": false
      },
      "live": false
    },
    {
      "index": 517,
      "broadcastIndex": 67,
      "liveEndDate": "2019-10-17T15:19:17",
      "originPrice": 5000,
      "salePrice": 4000,
      "discountRate": 20,
      "product": {
        "number": 511743,
        "name": "개별 - 무료 - 추가배송비 없음",
        "promotion": "개별배송 - 무료 배송 - 추가배송비 없음",
        "maxQuantity": 5,
        "stokeCount": 20,
        "reviewCount": 0,
        "averageRating": 0,
        "coupons": [],
        "imageUrls": {
          "origin": "https://sauce.kr.object.ncloudstorage.com/mall/dev/product/511743/15373013015d6777541420d9.698004331567061844.jpg",
          "basic": "https://sauce.kr.object.ncloudstorage.com/mall/dev/product/511743/90x90/15373013015d6777541420d9.698004331567061844.jpg",
          "twice": "https://sauce.kr.object.ncloudstorage.com/mall/dev/product/511743/180x180/15373013015d6777541420d9.698004331567061844.jpg",
          "triple": "https://sauce.kr.object.ncloudstorage.com/mall/dev/product/511743/270x270/15373013015d6777541420d9.698004331567061844.jpg"
        },
        "delivery": {
          "type": 0,
          "fee": 0,
          "freeAmount": 0,
          "package": false
        },
        "soldOut": false,
        "endOfSale": false
      },
      "live": false
    },
    {
      "index": 515,
      "broadcastIndex": 67,
      "liveEndDate": "2019-10-17T15:19:17",
      "originPrice": 6000,
      "salePrice": 4000,
      "discountRate": 33,
      "product": {
        "number": 511744,
        "name": "개별 - 착불 - 3300 - 추가배송비 없음",
        "promotion": "개별배송 - 착불 - 3300 - 추가배송비 없음",
        "maxQuantity": 2,
        "stokeCount": 5,
        "reviewCount": 0,
        "averageRating": 0,
        "coupons": [],
        "imageUrls": {
          "origin": "https://sauce.kr.object.ncloudstorage.com/mall/dev/product/511744/11593629795d6778155872c9.831672001567062037.jpg",
          "basic": "https://sauce.kr.object.ncloudstorage.com/mall/dev/product/511744/90x90/11593629795d6778155872c9.831672001567062037.jpg",
          "twice": "https://sauce.kr.object.ncloudstorage.com/mall/dev/product/511744/180x180/11593629795d6778155872c9.831672001567062037.jpg",
          "triple": "https://sauce.kr.object.ncloudstorage.com/mall/dev/product/511744/270x270/11593629795d6778155872c9.831672001567062037.jpg"
        },
        "delivery": {
          "type": 1,
          "fee": 3300,
          "freeAmount": 0,
          "package": false
        },
        "soldOut": false,
        "endOfSale": false
      },
      "live": false
    },
    {
      "index": 516,
      "broadcastIndex": 67,
      "liveEndDate": "2019-10-17T15:19:17",
      "originPrice": 7500,
      "salePrice": 5500,
      "discountRate": 27,
      "product": {
        "number": 511745,
        "name": "개별 - 선불 - 2800 - 추가배송비 없음",
        "promotion": "개별배송 - 선불 - 2800 - 추가배송비 없음",
        "maxQuantity": 1,
        "stokeCount": 6,
        "reviewCount": 0,
        "averageRating": 0,
        "coupons": [],
        "imageUrls": {
          "origin": "https://sauce.kr.object.ncloudstorage.com/mall/dev/product/511745/11019559845d677887d195d1.763175881567062151.jpg",
          "basic": "https://sauce.kr.object.ncloudstorage.com/mall/dev/product/511745/90x90/11019559845d677887d195d1.763175881567062151.jpg",
          "twice": "https://sauce.kr.object.ncloudstorage.com/mall/dev/product/511745/180x180/11019559845d677887d195d1.763175881567062151.jpg",
          "triple": "https://sauce.kr.object.ncloudstorage.com/mall/dev/product/511745/270x270/11019559845d677887d195d1.763175881567062151.jpg"
        },
        "delivery": {
          "type": 2,
          "fee": 2800,
          "freeAmount": 0,
          "package": false
        },
        "soldOut": false,
        "endOfSale": false
      },
      "live": false
    }
  ]
}